bbfreport/__init__.py
bbfreport/commonmark.py
bbfreport/content.py
bbfreport/exception.py
bbfreport/file.py
bbfreport/format.py
bbfreport/layout.py
bbfreport/logging.py
bbfreport/macro.py
bbfreport/main.py
bbfreport/node.py
bbfreport/pandoc.py
bbfreport/parser.py
bbfreport/path.py
bbfreport/plugin.py
bbfreport/property.py
bbfreport/transform.py
bbfreport/utility.py
bbfreport/version.py
bbfreport/visitor.py
bbfreport/macros/__init__.py
bbfreport/macros/macros.py
bbfreport/macros/test.py
bbfreport/plugins/__init__.py
bbfreport/plugins/automodel-transform.py
bbfreport/plugins/csv-format.py
bbfreport/plugins/depend-format.py
bbfreport/plugins/diff-transform.py
bbfreport/plugins/difflint-transform.py
bbfreport/plugins/difftext-format.py
bbfreport/plugins/dump-transform.py
bbfreport/plugins/expat-parser.py
bbfreport/plugins/hidefirst-transform.py
bbfreport/plugins/html-format.py
bbfreport/plugins/lint-transform.py
bbfreport/plugins/markdown-format.py
bbfreport/plugins/null-format.py
bbfreport/plugins/path-format.py
bbfreport/plugins/split-transform.py
bbfreport/plugins/text-format.py
bbfreport/plugins/used-transform.py
bbfreport/plugins/xml-format.py
bbfreport/plugins/examples/__init__.py
bbfreport/plugins/examples/candeny-transform.py
bbfreport/plugins/examples/edit-transform.py
bbfreport/plugins/examples/enum-transform.py
bbfreport/plugins/examples/pyxb-parser.py
bbfreport/plugins/examples/relref-transform.py
bbfreport/plugins/examples/status-transform.py
bbfreport/plugins/examples/version-transform.py
bbfreport/plugins/examples/xmltodict-parser.py
bbfreport/plugins/shared/__init__.py
bbfreport/plugins/shared/markdown.py
bbfreport-2.4.0.dist-info/licenses/LICENSE
bbfreport-2.4.0.dist-info/METADATA
bbfreport-2.4.0.dist-info/WHEEL
bbfreport-2.4.0.dist-info/entry_points.txt
bbfreport-2.4.0.dist-info/top_level.txt
bbfreport-2.4.0.dist-info/RECORD
