Metadata-Version: 2.4
Name: bbfreport
Version: 2.4.0
Summary: Broadband Forum (BBF) Data Model Report Tool
Author-email: William Lupton <wlupton@broadband-forum.org>
License-Expression: BSD-3-Clause
Project-URL: Homepage, https://github.com/BroadbandForum/bbfreport
Project-URL: Bug Tracker, https://github.com/BroadbandForum/bbfreport/issues
Classifier: Programming Language :: Python :: 3
Classifier: Operating System :: OS Independent
Requires-Python: >=3.11
License-File: LICENSE
Requires-Dist: markdown-it-py>=3.0.0
Requires-Dist: mdit-py-plugins>=0.4.2
Dynamic: license-file
